{
    "operator": {
        "id": "char_242_otter",
        "name": "Mayer",
        "rarity": 5,
        "portait": "",
        "profession": "SUPPORT",
        "subProfession": "summoner",
        "nation": "columbia",
        "group": "rhine",
        "displayNumber": "RL05",
        "position": "RANGED",
        "tagList": [
            "Summon",
            "Crowd-Control"
        ],
        "skins": [],
        "phases": [
            0,
            1,
            2
        ],
        "skills": [
            "skchr_otter_1",
            "skchr_otter_2"
        ],
        "talents": [
            1
        ]
    },
    "phases": [
        {
            "range": "3-6",
            "maxLevel": 50,
            "minStats": {
                "maxHP": 480,
                "atk": 199,
                "def": 56,
                "res": 15.0,
                "cost": 9,
                "baseAttackTime": 1.6,
                "respawnTime": 70,
                "taunt": 0
            },
            "maxStats": {
                "maxHP": 649,
                "atk": 285,
                "def": 80,
                "res": 15.0,
                "cost": 9,
                "baseAttackTime": 1.6,
                "respawnTime": 70,
                "taunt": 0
            }
        },
        {
            "range": "3-1",
            "maxLevel": 70,
            "minStats": {
                "maxHP": 649,
                "atk": 285,
                "def": 80,
                "res": 20.0,
                "cost": 11,
                "baseAttackTime": 1.6,
                "respawnTime": 70,
                "taunt": 0
            },
            "maxStats": {
                "maxHP": 843,
                "atk": 380,
                "def": 107,
                "res": 20.0,
                "cost": 11,
                "baseAttackTime": 1.6,
                "respawnTime": 70,
                "taunt": 0
            }
        },
        {
            "range": "3-1",
            "maxLevel": 80,
            "minStats": {
                "maxHP": 843,
                "atk": 380,
                "def": 107,
                "res": 20.0,
                "cost": 11,
                "baseAttackTime": 1.6,
                "respawnTime": 70,
                "taunt": 0
            },
            "maxStats": {
                "maxHP": 1068,
                "atk": 443,
                "def": 130,
                "res": 20.0,
                "cost": 11,
                "baseAttackTime": 1.6,
                "respawnTime": 70,
                "taunt": 0
            }
        }
    ],
    "talents": [
        {
            "name": "Robotter",
            "candidates": [
                {
                    "unlockPhase": 0,
                    "unlockPotentialRank": 0,
                    "description": "Can summon 3 Robotters; Enemies have -10 ASPD when blocked by Robotters",
                    "blackboard": {
                        "cnt": 3.0
                    }
                },
                {
                    "unlockPhase": 1,
                    "unlockPotentialRank": 0,
                    "description": "Can summon 4 Robotters; Enemies have -25 ASPD when blocked by Robotters",
                    "blackboard": {
                        "cnt": 4.0
                    }
                },
                {
                    "unlockPhase": 2,
                    "unlockPotentialRank": 0,
                    "description": "Can summon 5 Robotters; Enemies have -25 ASPD when blocked by Robotters",
                    "blackboard": {
                        "cnt": 5.0
                    }
                }
            ]
        }
    ],
    "potentialRanks": [
        {
            "type": "BUFF",
            "description": "DP Cost -1",
            "attribute": "COST",
            "formula": "ADDITION",
            "value": -1.0
        },
        {
            "type": "BUFF",
            "description": "Redeployment Time -4 sec",
            "attribute": "RESPAWN_TIME",
            "formula": "ADDITION",
            "value": -4.0
        },
        {
            "type": "BUFF",
            "description": "RES +8",
            "attribute": "MAGIC_RESISTANCE",
            "formula": "ADDITION",
            "value": 8.0
        },
        {
            "type": "BUFF",
            "description": "Redeployment Time -6 sec",
            "attribute": "RESPAWN_TIME",
            "formula": "ADDITION",
            "value": -6.0
        },
        {
            "type": "BUFF",
            "description": "DP Cost -1",
            "attribute": "COST",
            "formula": "ADDITION",
            "value": -1.0
        }
    ],
    "trait": {
        "description": "Deals <@ba.kw>Arts damage</>\nCan use <@ba.kw>Summons</> in battles",
        "candidates": []
    },
    "favor": {
        "maxHP": 200,
        "atk": 35,
        "def": 0,
        "res": 0.0,
        "cost": 0,
        "baseAttackTime": 0.0,
        "respawnTime": 0,
        "taunt": 0
    }
}