{
    "operator": {
        "id": "char_4065_judge",
        "name": "Penance",
        "rarity": 6,
        "portait": "",
        "profession": "TANK",
        "subProfession": "unyield",
        "nation": "siracusa",
        "group": null,
        "displayNumber": "SR35",
        "position": "MELEE",
        "tagList": [
            "Survival",
            "DPS"
        ],
        "skins": [],
        "phases": [
            0,
            1,
            2
        ],
        "skills": [
            "skchr_judge_1",
            "skchr_judge_2",
            "skchr_judge_3"
        ],
        "talents": [
            1,
            2
        ]
    },
    "phases": [
        {
            "range": "1-1",
            "maxLevel": 50,
            "minStats": {
                "maxHP": 1732,
                "atk": 368,
                "def": 234,
                "res": 10.0,
                "cost": 32,
                "baseAttackTime": 1.6,
                "respawnTime": 70,
                "taunt": 0
            },
            "maxStats": {
                "maxHP": 2279,
                "atk": 512,
                "def": 355,
                "res": 10.0,
                "cost": 32,
                "baseAttackTime": 1.6,
                "respawnTime": 70,
                "taunt": 0
            }
        },
        {
            "range": "1-1",
            "maxLevel": 80,
            "minStats": {
                "maxHP": 2279,
                "atk": 512,
                "def": 355,
                "res": 10.0,
                "cost": 34,
                "baseAttackTime": 1.6,
                "respawnTime": 70,
                "taunt": 0
            },
            "maxStats": {
                "maxHP": 2960,
                "atk": 683,
                "def": 474,
                "res": 10.0,
                "cost": 34,
                "baseAttackTime": 1.6,
                "respawnTime": 70,
                "taunt": 0
            }
        },
        {
            "range": "1-1",
            "maxLevel": 90,
            "minStats": {
                "maxHP": 2960,
                "atk": 683,
                "def": 474,
                "res": 10.0,
                "cost": 36,
                "baseAttackTime": 1.6,
                "respawnTime": 70,
                "taunt": 0
            },
            "maxStats": {
                "maxHP": 4055,
                "atk": 876,
                "def": 616,
                "res": 10.0,
                "cost": 36,
                "baseAttackTime": 1.6,
                "respawnTime": 70,
                "taunt": 0
            }
        }
    ],
    "talents": [
        {
            "name": "Guardian of the Law",
            "candidates": [
                {
                    "unlockPhase": 0,
                    "unlockPotentialRank": 0,
                    "description": "After deployment, immediately gains a <$ba.barrier>Barrier</> equal to 30% Max HP",
                    "blackboard": {
                        "max_hp_ratio": 3.0,
                        "kill_hp_ratio": 0.0,
                        "born_hp_ratio": 0.3,
                        "higher_effect_hp_ratio": 1.0
                    }
                },
                {
                    "unlockPhase": 0,
                    "unlockPotentialRank": 2,
                    "description": "After deployment, immediately gains a <$ba.barrier>Barrier</> equal to 35% <@ba.talpu>(+5%)</> Max HP",
                    "blackboard": {
                        "max_hp_ratio": 3.0,
                        "kill_hp_ratio": 0.0,
                        "born_hp_ratio": 0.35,
                        "higher_effect_hp_ratio": 1.0
                    }
                },
                {
                    "unlockPhase": 1,
                    "unlockPotentialRank": 0,
                    "description": "After deployment, immediately gains a <$ba.barrier>Barrier</> equal to 30% Max HP; When defeating an enemy, gains a <$ba.barrier>Barrier</> equal to 6% Max HP (Cannot exceed 300% Max HP)",
                    "blackboard": {
                        "max_hp_ratio": 3.0,
                        "kill_hp_ratio": 0.06,
                        "born_hp_ratio": 0.3,
                        "higher_effect_hp_ratio": 1.0
                    }
                },
                {
                    "unlockPhase": 1,
                    "unlockPotentialRank": 2,
                    "description": "After deployment, immediately gains a <$ba.barrier>Barrier</> equal to 35% <@ba.talpu>(+5%)</> Max HP; When defeating an enemy, gains a <$ba.barrier>Barrier</> equal to 6% Max HP (Cannot exceed 300% Max HP)",
                    "blackboard": {
                        "max_hp_ratio": 3.0,
                        "kill_hp_ratio": 0.06,
                        "born_hp_ratio": 0.35,
                        "higher_effect_hp_ratio": 1.0
                    }
                },
                {
                    "unlockPhase": 2,
                    "unlockPotentialRank": 0,
                    "description": "After deployment, immediately gains a <$ba.barrier>Barrier</> equal to 50% Max HP; When defeating an enemy, gains a <$ba.barrier>Barrier</> equal to 10% Max HP (Cannot exceed 300% Max HP)",
                    "blackboard": {
                        "max_hp_ratio": 3.0,
                        "kill_hp_ratio": 0.1,
                        "born_hp_ratio": 0.5,
                        "higher_effect_hp_ratio": 1.0
                    }
                },
                {
                    "unlockPhase": 2,
                    "unlockPotentialRank": 2,
                    "description": "After deployment, immediately gains a <$ba.barrier>Barrier</> equal to 55% <@ba.talpu>(+5%)</> Max HP; When defeating an enemy, gains a <$ba.barrier>Barrier</> equal to 10% Max HP (Cannot exceed 300% Max HP)",
                    "blackboard": {
                        "max_hp_ratio": 3.0,
                        "kill_hp_ratio": 0.1,
                        "born_hp_ratio": 0.55,
                        "higher_effect_hp_ratio": 1.0
                    }
                }
            ]
        },
        {
            "name": "Wreathed in Thorns",
            "candidates": [
                {
                    "unlockPhase": 2,
                    "unlockPotentialRank": 0,
                    "description": "Each time this unit is attacked while under the effect of her own <$ba.barrier>Barrier</>, deals 50% ATK as Arts damage to the attacker",
                    "blackboard": {
                        "atk_scale": 0.5
                    }
                },
                {
                    "unlockPhase": 2,
                    "unlockPotentialRank": 4,
                    "description": "Each time this unit is attacked while under the effect of her own <$ba.barrier>Barrier</>, deals 53% <@ba.talpu>(+3%)</> ATK as Arts damage to the attacker",
                    "blackboard": {
                        "atk_scale": 0.53
                    }
                }
            ]
        }
    ],
    "potentialRanks": [
        {
            "type": "BUFF",
            "description": "DP Cost -1",
            "attribute": "COST",
            "formula": "ADDITION",
            "value": -1.0
        },
        {
            "type": "CUSTOM",
            "description": "Improves First Talent"
        },
        {
            "type": "BUFF",
            "description": "ATK +28",
            "attribute": "ATK",
            "formula": "ADDITION",
            "value": 28.0
        },
        {
            "type": "CUSTOM",
            "description": "Improves Second Talent"
        },
        {
            "type": "BUFF",
            "description": "DP Cost -1",
            "attribute": "COST",
            "formula": "ADDITION",
            "value": -1.0
        }
    ],
    "trait": {
        "description": "<@ba.kw>Cannot</> be healed by allies",
        "candidates": []
    },
    "favor": {
        "maxHP": 600,
        "atk": 40,
        "def": 0,
        "res": 0.0,
        "cost": 0,
        "baseAttackTime": 0.0,
        "respawnTime": 0,
        "taunt": 0
    }
}