{
    "operator": {
        "id": "char_154_morgan",
        "name": "Morgan",
        "rarity": 5,
        "portait": "",
        "profession": "WARRIOR",
        "subProfession": "fearless",
        "nation": "victoria",
        "group": "glasgow",
        "displayNumber": "GG02",
        "position": "MELEE",
        "tagList": [
            "DPS"
        ],
        "skins": [],
        "phases": [
            0,
            1,
            2
        ],
        "skills": [
            "skchr_morgan_1",
            "skchr_morgan_2"
        ],
        "talents": [
            1,
            2
        ]
    },
    "phases": [
        {
            "range": "1-1",
            "maxLevel": 50,
            "minStats": {
                "maxHP": 1459,
                "atk": 403,
                "def": 107,
                "res": 0.0,
                "cost": 18,
                "baseAttackTime": 1.5,
                "respawnTime": 80,
                "taunt": 0
            },
            "maxStats": {
                "maxHP": 2085,
                "atk": 593,
                "def": 154,
                "res": 0.0,
                "cost": 18,
                "baseAttackTime": 1.5,
                "respawnTime": 80,
                "taunt": 0
            }
        },
        {
            "range": "1-1",
            "maxLevel": 70,
            "minStats": {
                "maxHP": 2085,
                "atk": 593,
                "def": 154,
                "res": 0.0,
                "cost": 20,
                "baseAttackTime": 1.5,
                "respawnTime": 80,
                "taunt": 0
            },
            "maxStats": {
                "maxHP": 2857,
                "atk": 751,
                "def": 201,
                "res": 0.0,
                "cost": 20,
                "baseAttackTime": 1.5,
                "respawnTime": 80,
                "taunt": 0
            }
        },
        {
            "range": "1-1",
            "maxLevel": 80,
            "minStats": {
                "maxHP": 2857,
                "atk": 751,
                "def": 201,
                "res": 0.0,
                "cost": 20,
                "baseAttackTime": 1.5,
                "respawnTime": 80,
                "taunt": 0
            },
            "maxStats": {
                "maxHP": 3810,
                "atk": 905,
                "def": 243,
                "res": 0.0,
                "cost": 20,
                "baseAttackTime": 1.5,
                "respawnTime": 80,
                "taunt": 0
            }
        }
    ],
    "talents": [
        {
            "name": "Hot-Blooded Vanguard",
            "candidates": [
                {
                    "unlockPhase": 1,
                    "unlockPotentialRank": 0,
                    "description": "Gains up to +40% ATK <$ba.berserk>Tenacity</> (reaches maximum bonus when losing 70% Max HP)",
                    "blackboard": {
                        "min_atk": 0.4,
                        "min_hp_ratio": 0.3
                    }
                },
                {
                    "unlockPhase": 1,
                    "unlockPotentialRank": 4,
                    "description": "Gains up to +42% <@ba.talpu>(+2%)</> ATK <$ba.berserk>Tenacity</> (reaches maximum bonus when losing 70% Max HP)",
                    "blackboard": {
                        "min_atk": 0.42,
                        "min_hp_ratio": 0.3
                    }
                },
                {
                    "unlockPhase": 2,
                    "unlockPotentialRank": 0,
                    "description": "Gains up to +50% ATK <$ba.berserk>Tenacity</> (reaches maximum bonus when losing 70% Max HP)",
                    "blackboard": {
                        "min_atk": 0.5,
                        "min_hp_ratio": 0.3
                    }
                },
                {
                    "unlockPhase": 2,
                    "unlockPotentialRank": 4,
                    "description": "Gains up to +52% <@ba.talpu>(+2%)</> ATK <$ba.berserk>Tenacity</> (reaches maximum bonus when losing 70% Max HP)",
                    "blackboard": {
                        "min_atk": 0.52,
                        "min_hp_ratio": 0.3
                    }
                }
            ]
        },
        {
            "name": "Home-Ground Advantage",
            "candidates": [
                {
                    "unlockPhase": 2,
                    "unlockPotentialRank": 0,
                    "description": "Deployment does not consume Deployment Slots in 'All Quiet Under The Thunder'",
                    "blackboard": {}
                }
            ]
        }
    ],
    "potentialRanks": [
        {
            "type": "BUFF",
            "description": "DP Cost -1",
            "attribute": "COST",
            "formula": "ADDITION",
            "value": -1.0
        },
        {
            "type": "BUFF",
            "description": "Redeployment Time -10 sec",
            "attribute": "RESPAWN_TIME",
            "formula": "ADDITION",
            "value": -10.0
        },
        {
            "type": "BUFF",
            "description": "DP Cost -1",
            "attribute": "COST",
            "formula": "ADDITION",
            "value": -1.0
        },
        {
            "type": "CUSTOM",
            "description": "Improves First Talent"
        },
        {
            "type": "BUFF",
            "description": "DP Cost -1",
            "attribute": "COST",
            "formula": "ADDITION",
            "value": -1.0
        }
    ],
    "trait": {
        "description": "Blocks 1 enemy",
        "candidates": []
    },
    "favor": {
        "maxHP": 0,
        "atk": 75,
        "def": 25,
        "res": 0.0,
        "cost": 0,
        "baseAttackTime": 0.0,
        "respawnTime": 0,
        "taunt": 0
    }
}