{
    "operator": {
        "id": "char_298_susuro",
        "name": "Sussurro",
        "rarity": 4,
        "portait": "",
        "profession": "MEDIC",
        "subProfession": "physician",
        "nation": "rhodes",
        "group": null,
        "displayNumber": "R107",
        "position": "RANGED",
        "tagList": [
            "Healing"
        ],
        "skins": [],
        "phases": [
            0,
            1,
            2
        ],
        "skills": [
            "skcom_heal_up[2]",
            "skchr_susuro_2"
        ],
        "talents": [
            1
        ]
    },
    "phases": [
        {
            "range": "3-1",
            "maxLevel": 45,
            "minStats": {
                "maxHP": 725,
                "atk": 173,
                "def": 53,
                "res": 0.0,
                "cost": 16,
                "baseAttackTime": 2.85,
                "respawnTime": 70,
                "taunt": 0
            },
            "maxStats": {
                "maxHP": 994,
                "atk": 284,
                "def": 77,
                "res": 0.0,
                "cost": 16,
                "baseAttackTime": 2.85,
                "respawnTime": 70,
                "taunt": 0
            }
        },
        {
            "range": "3-3",
            "maxLevel": 60,
            "minStats": {
                "maxHP": 994,
                "atk": 284,
                "def": 77,
                "res": 0.0,
                "cost": 18,
                "baseAttackTime": 2.85,
                "respawnTime": 70,
                "taunt": 0
            },
            "maxStats": {
                "maxHP": 1170,
                "atk": 395,
                "def": 97,
                "res": 0.0,
                "cost": 18,
                "baseAttackTime": 2.85,
                "respawnTime": 70,
                "taunt": 0
            }
        },
        {
            "range": "3-3",
            "maxLevel": 70,
            "minStats": {
                "maxHP": 1170,
                "atk": 395,
                "def": 97,
                "res": 0.0,
                "cost": 18,
                "baseAttackTime": 2.85,
                "respawnTime": 70,
                "taunt": 0
            },
            "maxStats": {
                "maxHP": 1345,
                "atk": 488,
                "def": 122,
                "res": 0.0,
                "cost": 18,
                "baseAttackTime": 2.85,
                "respawnTime": 70,
                "taunt": 0
            }
        }
    ],
    "talents": [
        {
            "name": "Minimally Invasive Surgery",
            "candidates": [
                {
                    "unlockPhase": 1,
                    "unlockPotentialRank": 0,
                    "description": "Increases healing effects by 10% on all Operators with DP Cost no more than 10 when Sussurro is in the squad",
                    "blackboard": {
                        "cost": 10.0,
                        "heal_scale": 1.1
                    }
                },
                {
                    "unlockPhase": 1,
                    "unlockPotentialRank": 4,
                    "description": "Increases healing effects by 13%<@ba.talpu> (+3%)</> on all Operators with DP Cost no more than 10 when Sussurro is in the squad",
                    "blackboard": {
                        "cost": 10.0,
                        "heal_scale": 1.13
                    }
                },
                {
                    "unlockPhase": 2,
                    "unlockPotentialRank": 0,
                    "description": "Increases healing effects by 20% on all Operators with DP Cost no more than 10 when Sussurro is in the squad",
                    "blackboard": {
                        "cost": 10.0,
                        "heal_scale": 1.2
                    }
                },
                {
                    "unlockPhase": 2,
                    "unlockPotentialRank": 4,
                    "description": "Increases healing effects by 23%<@ba.talpu> (+3%)</> on all Operators with DP Cost no more than 10 when Sussurro is in the squad",
                    "blackboard": {
                        "cost": 10.0,
                        "heal_scale": 1.23
                    }
                }
            ]
        }
    ],
    "potentialRanks": [
        {
            "type": "BUFF",
            "description": "DP Cost -1",
            "attribute": "COST",
            "formula": "ADDITION",
            "value": -1.0
        },
        {
            "type": "BUFF",
            "description": "Redeployment Time -4 sec",
            "attribute": "RESPAWN_TIME",
            "formula": "ADDITION",
            "value": -4.0
        },
        {
            "type": "BUFF",
            "description": "ATK +23",
            "attribute": "ATK",
            "formula": "ADDITION",
            "value": 23.0
        },
        {
            "type": "CUSTOM",
            "description": "Improves Talent"
        },
        {
            "type": "BUFF",
            "description": "DP Cost -1",
            "attribute": "COST",
            "formula": "ADDITION",
            "value": -1.0
        }
    ],
    "trait": {
        "description": "Restores the HP of allies",
        "candidates": []
    },
    "favor": {
        "maxHP": 0,
        "atk": 60,
        "def": 0,
        "res": 0.0,
        "cost": 0,
        "baseAttackTime": 0.0,
        "respawnTime": 0,
        "taunt": 0
    }
}