{
    "id": "skchr_acfend_2",
    "name": "Invariance Principle",
    "skillType": "MANUAL",
    "durationType": "NONE",
    "spType": "INCREASE_WITH_TIME",
    "levels": [
        {
            "description": "DEF <@ba.vup>+{def:0%}</>, Talent 2's effect increases to <@ba.vup>{talent_mult}</>x",
            "maxCharge": 1,
            "spCost": 48,
            "initSp": 5,
            "duration": 20.0,
            "blackboard": {
                "def": 0.35,
                "talent_mult": 2.0
            }
        },
        {
            "description": "DEF <@ba.vup>+{def:0%}</>, Talent 2's effect increases to <@ba.vup>{talent_mult}</>x",
            "maxCharge": 1,
            "spCost": 46,
            "initSp": 5,
            "duration": 20.0,
            "blackboard": {
                "def": 0.4,
                "talent_mult": 2.0
            }
        },
        {
            "description": "DEF <@ba.vup>+{def:0%}</>, Talent 2's effect increases to <@ba.vup>{talent_mult}</>x",
            "maxCharge": 1,
            "spCost": 44,
            "initSp": 5,
            "duration": 20.0,
            "blackboard": {
                "def": 0.45,
                "talent_mult": 2.0
            }
        },
        {
            "description": "DEF <@ba.vup>+{def:0%}</>, Talent 2's effect increases to <@ba.vup>{talent_mult}</>x",
            "maxCharge": 1,
            "spCost": 42,
            "initSp": 10,
            "duration": 20.0,
            "blackboard": {
                "def": 0.5,
                "talent_mult": 2.0
            }
        },
        {
            "description": "DEF <@ba.vup>+{def:0%}</>, Talent 2's effect increases to <@ba.vup>{talent_mult}</>x",
            "maxCharge": 1,
            "spCost": 40,
            "initSp": 10,
            "duration": 20.0,
            "blackboard": {
                "def": 0.55,
                "talent_mult": 2.0
            }
        },
        {
            "description": "DEF <@ba.vup>+{def:0%}</>, Talent 2's effect increases to <@ba.vup>{talent_mult}</>x",
            "maxCharge": 1,
            "spCost": 38,
            "initSp": 10,
            "duration": 20.0,
            "blackboard": {
                "def": 0.6,
                "talent_mult": 2.0
            }
        },
        {
            "description": "DEF <@ba.vup>+{def:0%}</>, Talent 2's effect increases to <@ba.vup>{talent_mult}</>x",
            "maxCharge": 1,
            "spCost": 35,
            "initSp": 15,
            "duration": 20.0,
            "blackboard": {
                "def": 0.65,
                "talent_mult": 3.0
            }
        },
        {
            "description": "DEF <@ba.vup>+{def:0%}</>, Talent 2's effect increases to <@ba.vup>{talent_mult}</>x",
            "maxCharge": 1,
            "spCost": 33,
            "initSp": 15,
            "duration": 20.0,
            "blackboard": {
                "def": 0.7,
                "talent_mult": 3.0
            }
        },
        {
            "description": "DEF <@ba.vup>+{def:0%}</>, Talent 2's effect increases to <@ba.vup>{talent_mult}</>x",
            "maxCharge": 1,
            "spCost": 33,
            "initSp": 15,
            "duration": 20.0,
            "blackboard": {
                "def": 0.75,
                "talent_mult": 3.0
            }
        },
        {
            "description": "DEF <@ba.vup>+{def:0%}</>, Talent 2's effect increases to <@ba.vup>{talent_mult}</>x",
            "maxCharge": 1,
            "spCost": 30,
            "initSp": 15,
            "duration": 20.0,
            "blackboard": {
                "def": 0.8,
                "talent_mult": 3.0
            }
        }
    ]
}