{
    "id": "skchr_logos_3",
    "name": "Extended Acuity",
    "skillType": "MANUAL",
    "durationType": "NONE",
    "spType": "INCREASE_WITH_TIME",
    "levels": [
        {
            "description": "Attack range <@ba.vup>expands</>, ATK <@ba.vup>+{atk:0%}</>, and attacks strike <@ba.vup>{attack@max_target}</> targets at once; enemy projectile speed in attack range is <@ba.vup>greatly reduced</>, and all projectiles are <@ba.vup>removed</> when the skill expires.",
            "range": "3-4",
            "maxCharge": 1,
            "spCost": 45,
            "initSp": 0,
            "duration": 30.0,
            "blackboard": {
                "atk": 1.0,
                "attack@max_target": 3.0,
                "projectile_move_scale": 0.05
            }
        },
        {
            "description": "Attack range <@ba.vup>expands</>, ATK <@ba.vup>+{atk:0%}</>, and attacks strike <@ba.vup>{attack@max_target}</> targets at once; enemy projectile speed in attack range is <@ba.vup>greatly reduced</>, and all projectiles are <@ba.vup>removed</> when the skill expires.",
            "range": "3-4",
            "maxCharge": 1,
            "spCost": 45,
            "initSp": 3,
            "duration": 30.0,
            "blackboard": {
                "atk": 1.2,
                "attack@max_target": 3.0,
                "projectile_move_scale": 0.05
            }
        },
        {
            "description": "Attack range <@ba.vup>expands</>, ATK <@ba.vup>+{atk:0%}</>, and attacks strike <@ba.vup>{attack@max_target}</> targets at once; enemy projectile speed in attack range is <@ba.vup>greatly reduced</>, and all projectiles are <@ba.vup>removed</> when the skill expires.",
            "range": "3-4",
            "maxCharge": 1,
            "spCost": 45,
            "initSp": 6,
            "duration": 30.0,
            "blackboard": {
                "atk": 1.4,
                "attack@max_target": 3.0,
                "projectile_move_scale": 0.05
            }
        },
        {
            "description": "Attack range <@ba.vup>expands</>, ATK <@ba.vup>+{atk:0%}</>, and attacks strike <@ba.vup>{attack@max_target}</> targets at once; enemy projectile speed in attack range is <@ba.vup>greatly reduced</>, and all projectiles are <@ba.vup>removed</> when the skill expires.",
            "range": "3-4",
            "maxCharge": 1,
            "spCost": 45,
            "initSp": 9,
            "duration": 30.0,
            "blackboard": {
                "atk": 1.6,
                "attack@max_target": 3.0,
                "projectile_move_scale": 0.05
            }
        },
        {
            "description": "Attack range <@ba.vup>expands</>, ATK <@ba.vup>+{atk:0%}</>, and attacks strike <@ba.vup>{attack@max_target}</> targets at once; enemy projectile speed in attack range is <@ba.vup>greatly reduced</>, and all projectiles are <@ba.vup>removed</> when the skill expires.",
            "range": "3-4",
            "maxCharge": 1,
            "spCost": 45,
            "initSp": 12,
            "duration": 30.0,
            "blackboard": {
                "atk": 1.8,
                "attack@max_target": 3.0,
                "projectile_move_scale": 0.05
            }
        },
        {
            "description": "Attack range <@ba.vup>expands</>, ATK <@ba.vup>+{atk:0%}</>, and attacks strike <@ba.vup>{attack@max_target}</> targets at once; enemy projectile speed in attack range is <@ba.vup>greatly reduced</>, and all projectiles are <@ba.vup>removed</> when the skill expires.",
            "range": "3-4",
            "maxCharge": 1,
            "spCost": 45,
            "initSp": 15,
            "duration": 30.0,
            "blackboard": {
                "atk": 2.0,
                "attack@max_target": 3.0,
                "projectile_move_scale": 0.05
            }
        },
        {
            "description": "Attack range <@ba.vup>expands</>, ATK <@ba.vup>+{atk:0%}</>, and attacks strike <@ba.vup>{attack@max_target}</> targets at once; enemy projectile speed in attack range is <@ba.vup>greatly reduced</>, and all projectiles are <@ba.vup>removed</> when the skill expires.",
            "range": "3-4",
            "maxCharge": 1,
            "spCost": 45,
            "initSp": 18,
            "duration": 30.0,
            "blackboard": {
                "atk": 2.2,
                "attack@max_target": 3.0,
                "projectile_move_scale": 0.05
            }
        },
        {
            "description": "Attack range <@ba.vup>expands</>, ATK <@ba.vup>+{atk:0%}</>, and attacks strike <@ba.vup>{attack@max_target}</> targets at once; enemy projectile speed in attack range is <@ba.vup>greatly reduced</>, and all projectiles are <@ba.vup>removed</> when the skill expires.",
            "range": "3-4",
            "maxCharge": 1,
            "spCost": 45,
            "initSp": 22,
            "duration": 30.0,
            "blackboard": {
                "atk": 2.4,
                "attack@max_target": 4.0,
                "projectile_move_scale": 0.05
            }
        },
        {
            "description": "Attack range <@ba.vup>expands</>, ATK <@ba.vup>+{atk:0%}</>, and attacks strike <@ba.vup>{attack@max_target}</> targets at once; enemy projectile speed in attack range is <@ba.vup>greatly reduced</>, and all projectiles are <@ba.vup>removed</> when the skill expires.",
            "range": "3-4",
            "maxCharge": 1,
            "spCost": 45,
            "initSp": 26,
            "duration": 30.0,
            "blackboard": {
                "atk": 2.6,
                "attack@max_target": 4.0,
                "projectile_move_scale": 0.05
            }
        },
        {
            "description": "Attack range <@ba.vup>expands</>, ATK <@ba.vup>+{atk:0%}</>, and attacks strike <@ba.vup>{attack@max_target}</> targets at once; enemy projectile speed in attack range is <@ba.vup>greatly reduced</>, and all projectiles are <@ba.vup>removed</> when the skill expires.",
            "range": "3-4",
            "maxCharge": 1,
            "spCost": 45,
            "initSp": 30,
            "duration": 30.0,
            "blackboard": {
                "atk": 3.0,
                "attack@max_target": 4.0,
                "projectile_move_scale": 0.05
            }
        }
    ]
}