{
    "id": "skchr_chilc_2",
    "name": "Improvisation",
    "skillType": "MANUAL",
    "durationType": "NONE",
    "spType": "INCREASE_WITH_TIME",
    "levels": [
        {
            "description": "Gain <@ba.vup>{prob:0%}</> Physical Dodge, ASPD +<@ba.vup>{attack_speed}</>, and obtain <@ba.vup>{cost}</> DP with every attack",
            "maxCharge": 1,
            "spCost": 31,
            "initSp": 11,
            "duration": 10.0,
            "blackboard": {
                "attack_speed": 35.0,
                "prob": 0.3,
                "cost": 1.0
            }
        },
        {
            "description": "Gain <@ba.vup>{prob:0%}</> Physical Dodge, ASPD +<@ba.vup>{attack_speed}</>, and obtain <@ba.vup>{cost}</> DP with every attack",
            "maxCharge": 1,
            "spCost": 30,
            "initSp": 11,
            "duration": 10.0,
            "blackboard": {
                "attack_speed": 37.0,
                "prob": 0.3,
                "cost": 1.0
            }
        },
        {
            "description": "Gain <@ba.vup>{prob:0%}</> Physical Dodge, ASPD +<@ba.vup>{attack_speed}</>, and obtain <@ba.vup>{cost}</> DP with every attack",
            "maxCharge": 1,
            "spCost": 29,
            "initSp": 11,
            "duration": 10.0,
            "blackboard": {
                "attack_speed": 39.0,
                "prob": 0.3,
                "cost": 1.0
            }
        },
        {
            "description": "Gain <@ba.vup>{prob:0%}</> Physical Dodge, ASPD +<@ba.vup>{attack_speed}</>, and obtain <@ba.vup>{cost}</> DP with every attack",
            "maxCharge": 1,
            "spCost": 28,
            "initSp": 12,
            "duration": 10.0,
            "blackboard": {
                "attack_speed": 42.0,
                "prob": 0.35,
                "cost": 1.0
            }
        },
        {
            "description": "Gain <@ba.vup>{prob:0%}</> Physical Dodge, ASPD +<@ba.vup>{attack_speed}</>, and obtain <@ba.vup>{cost}</> DP with every attack",
            "maxCharge": 1,
            "spCost": 27,
            "initSp": 12,
            "duration": 10.0,
            "blackboard": {
                "attack_speed": 44.0,
                "prob": 0.35,
                "cost": 1.0
            }
        },
        {
            "description": "Gain <@ba.vup>{prob:0%}</> Physical Dodge, ASPD +<@ba.vup>{attack_speed}</>, and obtain <@ba.vup>{cost}</> DP with every attack",
            "maxCharge": 1,
            "spCost": 26,
            "initSp": 12,
            "duration": 10.0,
            "blackboard": {
                "attack_speed": 46.0,
                "prob": 0.35,
                "cost": 1.0
            }
        },
        {
            "description": "Gain <@ba.vup>{prob:0%}</> Physical Dodge, ASPD +<@ba.vup>{attack_speed}</>, and obtain <@ba.vup>{cost}</> DP with every attack",
            "maxCharge": 1,
            "spCost": 25,
            "initSp": 14,
            "duration": 10.0,
            "blackboard": {
                "attack_speed": 50.0,
                "prob": 0.38,
                "cost": 1.0
            }
        },
        {
            "description": "Gain <@ba.vup>{prob:0%}</> Physical Dodge, ASPD +<@ba.vup>{attack_speed}</>, and obtain <@ba.vup>{cost}</> DP with every attack",
            "maxCharge": 1,
            "spCost": 24,
            "initSp": 15,
            "duration": 10.0,
            "blackboard": {
                "attack_speed": 54.0,
                "prob": 0.4,
                "cost": 1.0
            }
        },
        {
            "description": "Gain <@ba.vup>{prob:0%}</> Physical Dodge, ASPD +<@ba.vup>{attack_speed}</>, and obtain <@ba.vup>{cost}</> DP with every attack",
            "maxCharge": 1,
            "spCost": 23,
            "initSp": 16,
            "duration": 10.0,
            "blackboard": {
                "attack_speed": 57.0,
                "prob": 0.42,
                "cost": 1.0
            }
        },
        {
            "description": "Gain <@ba.vup>{prob:0%}</> Physical Dodge, ASPD +<@ba.vup>{attack_speed}</>, and obtain <@ba.vup>{cost}</> DP with every attack",
            "maxCharge": 1,
            "spCost": 22,
            "initSp": 17,
            "duration": 10.0,
            "blackboard": {
                "attack_speed": 60.0,
                "prob": 0.45,
                "cost": 1.0
            }
        }
    ]
}