{
    "id": "skchr_snsant_2",
    "name": "Telescoping Electric Net",
    "skillType": "MANUAL",
    "durationType": "NONE",
    "spType": "INCREASE_WITH_TIME",
    "levels": [
        {
            "description": "Launches a net forward, dragging all enemies caught within it towards this unit <@ba.vup>slightly</>, dealing <@ba.vup>{atk_scale:0%}</> ATK as <@ba.vup>Arts damage</> and <$ba.sluggish>Slowing</> them for <@ba.vup>{sluggish}</> seconds",
            "range": "3-2",
            "maxCharge": 1,
            "spCost": 27,
            "initSp": 10,
            "duration": 0.0,
            "blackboard": {
                "atk_scale": 1.3,
                "force": 0.0,
                "sluggish": 2.1
            }
        },
        {
            "description": "Launches a net forward, dragging all enemies caught within it towards this unit <@ba.vup>slightly</>, dealing <@ba.vup>{atk_scale:0%}</> ATK as <@ba.vup>Arts damage</> and <$ba.sluggish>Slowing</> them for <@ba.vup>{sluggish}</> seconds",
            "range": "3-2",
            "maxCharge": 1,
            "spCost": 26,
            "initSp": 10,
            "duration": 0.0,
            "blackboard": {
                "atk_scale": 1.35,
                "force": 0.0,
                "sluggish": 2.1
            }
        },
        {
            "description": "Launches a net forward, dragging all enemies caught within it towards this unit <@ba.vup>slightly</>, dealing <@ba.vup>{atk_scale:0%}</> ATK as <@ba.vup>Arts damage</> and <$ba.sluggish>Slowing</> them for <@ba.vup>{sluggish}</> seconds",
            "range": "3-2",
            "maxCharge": 1,
            "spCost": 25,
            "initSp": 10,
            "duration": 0.0,
            "blackboard": {
                "atk_scale": 1.4,
                "force": 0.0,
                "sluggish": 2.1
            }
        },
        {
            "description": "Launches a net forward, dragging all enemies caught within it towards this unit <@ba.vup>moderately</>, dealing <@ba.vup>{atk_scale:0%}</> ATK as <@ba.vup>Arts damage</> and <$ba.sluggish>Slowing</> them for <@ba.vup>{sluggish}</> seconds",
            "range": "3-2",
            "maxCharge": 1,
            "spCost": 24,
            "initSp": 10,
            "duration": 0.0,
            "blackboard": {
                "atk_scale": 1.45,
                "force": 1.0,
                "sluggish": 2.3
            }
        },
        {
            "description": "Launches a net forward, dragging all enemies caught within it towards this unit <@ba.vup>moderately</>, dealing <@ba.vup>{atk_scale:0%}</> ATK as <@ba.vup>Arts damage</> and <$ba.sluggish>Slowing</> them for <@ba.vup>{sluggish}</> seconds",
            "range": "3-2",
            "maxCharge": 1,
            "spCost": 23,
            "initSp": 10,
            "duration": 0.0,
            "blackboard": {
                "atk_scale": 1.5,
                "force": 1.0,
                "sluggish": 2.3
            }
        },
        {
            "description": "Launches a net forward, dragging all enemies caught within it towards this unit <@ba.vup>moderately</>, dealing <@ba.vup>{atk_scale:0%}</> ATK as <@ba.vup>Arts damage</> and <$ba.sluggish>Slowing</> them for <@ba.vup>{sluggish}</> seconds",
            "range": "3-2",
            "maxCharge": 1,
            "spCost": 22,
            "initSp": 10,
            "duration": 0.0,
            "blackboard": {
                "atk_scale": 1.55,
                "force": 1.0,
                "sluggish": 2.3
            }
        },
        {
            "description": "Launches a net forward, dragging all enemies caught within it towards this unit <@ba.vup>moderately</>, dealing <@ba.vup>{atk_scale:0%}</> ATK as <@ba.vup>Arts damage</> and <$ba.sluggish>Slowing</> them for <@ba.vup>{sluggish}</> seconds",
            "range": "3-2",
            "maxCharge": 1,
            "spCost": 21,
            "initSp": 10,
            "duration": 0.0,
            "blackboard": {
                "atk_scale": 1.6,
                "force": 1.0,
                "sluggish": 2.5
            }
        },
        {
            "description": "Launches a net forward, dragging all enemies caught within it towards this unit <@ba.vup>moderately</>, dealing <@ba.vup>{atk_scale:0%}</> ATK as <@ba.vup>Arts damage</> and <$ba.sluggish>Slowing</> them for <@ba.vup>{sluggish}</> seconds",
            "range": "3-2",
            "maxCharge": 1,
            "spCost": 20,
            "initSp": 10,
            "duration": 0.0,
            "blackboard": {
                "atk_scale": 1.7,
                "force": 1.0,
                "sluggish": 2.8
            }
        },
        {
            "description": "Launches a net forward, dragging all enemies caught within it towards this unit <@ba.vup>moderately</>, dealing <@ba.vup>{atk_scale:0%}</> ATK as <@ba.vup>Arts damage</> and <$ba.sluggish>Slowing</> them for <@ba.vup>{sluggish}</> seconds",
            "range": "3-2",
            "maxCharge": 1,
            "spCost": 19,
            "initSp": 10,
            "duration": 0.0,
            "blackboard": {
                "atk_scale": 1.8,
                "force": 1.0,
                "sluggish": 3.1
            }
        },
        {
            "description": "Launches a net forward, dragging all enemies caught within it towards this unit <@ba.vup>significantly</>, dealing <@ba.vup>{atk_scale:0%}</> ATK as <@ba.vup>Arts damage</> and <$ba.sluggish>Slowing</> them for <@ba.vup>{sluggish}</> seconds",
            "range": "3-2",
            "maxCharge": 1,
            "spCost": 17,
            "initSp": 10,
            "duration": 0.0,
            "blackboard": {
                "atk_scale": 2.0,
                "force": 2.0,
                "sluggish": 3.5
            }
        }
    ]
}