{
    "id": "skchr_crosly_3",
    "name": "Smokescreen Execution",
    "skillType": "PASSIVE",
    "durationType": "NONE",
    "spType": 8,
    "levels": [
        {
            "description": "After deployment, Talent 1's range expands; Crownslayer disappears within the smoke, gaining <$ba.invisible>Invisibility</> and her Block becomes 0; every <@ba.vup>{attack@times}</>s, she will appear and deal <@ba.vup>{attack@atk_scale_s3:0%}</> ATK as Physical damage twice to a ground enemy within the smoke and <$ba.stun>Stun</> them for <@ba.vup>{attack@stun}</>s (a single target can only be targeted once every <@ba.vup>{mark_duration}</>s)",
            "range": "x-1",
            "maxCharge": 0,
            "spCost": 0,
            "initSp": 0,
            "duration": 16.0,
            "blackboard": {
                "attack@s3_cd": 2.0,
                "attack@times": 2.0,
                "attack@hit_interval": 0.1,
                "attack@atk_scale_s3": 1.1,
                "attack@stun": 1.0,
                "mark_duration": 6.0
            }
        },
        {
            "description": "After deployment, Talent 1's range expands; Crownslayer disappears within the smoke, gaining <$ba.invisible>Invisibility</> and her Block becomes 0; every <@ba.vup>{attack@times}</>s, she will appear and deal <@ba.vup>{attack@atk_scale_s3:0%}</> ATK as Physical damage twice to a ground enemy within the smoke and <$ba.stun>Stun</> them for <@ba.vup>{attack@stun}</>s (a single target can only be targeted once every <@ba.vup>{mark_duration}</>s)",
            "range": "x-1",
            "maxCharge": 0,
            "spCost": 0,
            "initSp": 0,
            "duration": 16.0,
            "blackboard": {
                "attack@s3_cd": 2.0,
                "attack@times": 2.0,
                "attack@hit_interval": 0.1,
                "attack@atk_scale_s3": 1.2,
                "attack@stun": 1.0,
                "mark_duration": 6.0
            }
        },
        {
            "description": "After deployment, Talent 1's range expands; Crownslayer disappears within the smoke, gaining <$ba.invisible>Invisibility</> and her Block becomes 0; every <@ba.vup>{attack@times}</>s, she will appear and deal <@ba.vup>{attack@atk_scale_s3:0%}</> ATK as Physical damage twice to a ground enemy within the smoke and <$ba.stun>Stun</> them for <@ba.vup>{attack@stun}</>s (a single target can only be targeted once every <@ba.vup>{mark_duration}</>s)",
            "range": "x-1",
            "maxCharge": 0,
            "spCost": 0,
            "initSp": 0,
            "duration": 16.0,
            "blackboard": {
                "attack@s3_cd": 2.0,
                "attack@times": 2.0,
                "attack@hit_interval": 0.1,
                "attack@atk_scale_s3": 1.3,
                "attack@stun": 1.0,
                "mark_duration": 6.0
            }
        },
        {
            "description": "After deployment, Talent 1's range expands; Crownslayer disappears within the smoke, gaining <$ba.invisible>Invisibility</> and her Block becomes 0; every <@ba.vup>{attack@times}</>s, she will appear and deal <@ba.vup>{attack@atk_scale_s3:0%}</> ATK as Physical damage twice to a ground enemy within the smoke and <$ba.stun>Stun</> them for <@ba.vup>{attack@stun}</>s (a single target can only be targeted once every <@ba.vup>{mark_duration}</>s)",
            "range": "x-1",
            "maxCharge": 0,
            "spCost": 0,
            "initSp": 0,
            "duration": 16.0,
            "blackboard": {
                "attack@s3_cd": 2.0,
                "attack@times": 2.0,
                "attack@hit_interval": 0.1,
                "attack@atk_scale_s3": 1.5,
                "attack@stun": 1.5,
                "mark_duration": 6.0
            }
        },
        {
            "description": "After deployment, Talent 1's range expands; Crownslayer disappears within the smoke, gaining <$ba.invisible>Invisibility</> and her Block becomes 0; every <@ba.vup>{attack@times}</>s, she will appear and deal <@ba.vup>{attack@atk_scale_s3:0%}</> ATK as Physical damage twice to a ground enemy within the smoke and <$ba.stun>Stun</> them for <@ba.vup>{attack@stun}</>s (a single target can only be targeted once every <@ba.vup>{mark_duration}</>s)",
            "range": "x-1",
            "maxCharge": 0,
            "spCost": 0,
            "initSp": 0,
            "duration": 16.0,
            "blackboard": {
                "attack@s3_cd": 2.0,
                "attack@times": 2.0,
                "attack@hit_interval": 0.1,
                "attack@atk_scale_s3": 1.6,
                "attack@stun": 1.5,
                "mark_duration": 6.0
            }
        },
        {
            "description": "After deployment, Talent 1's range expands; Crownslayer disappears within the smoke, gaining <$ba.invisible>Invisibility</> and her Block becomes 0; every <@ba.vup>{attack@times}</>s, she will appear and deal <@ba.vup>{attack@atk_scale_s3:0%}</> ATK as Physical damage twice to a ground enemy within the smoke and <$ba.stun>Stun</> them for <@ba.vup>{attack@stun}</>s (a single target can only be targeted once every <@ba.vup>{mark_duration}</>s)",
            "range": "x-1",
            "maxCharge": 0,
            "spCost": 0,
            "initSp": 0,
            "duration": 16.0,
            "blackboard": {
                "attack@s3_cd": 2.0,
                "attack@times": 2.0,
                "attack@hit_interval": 0.1,
                "attack@atk_scale_s3": 1.7,
                "attack@stun": 1.5,
                "mark_duration": 6.0
            }
        },
        {
            "description": "After deployment, Talent 1's range expands; Crownslayer disappears within the smoke, gaining <$ba.invisible>Invisibility</> and her Block becomes 0; every <@ba.vup>{attack@times}</>s, she will appear and deal <@ba.vup>{attack@atk_scale_s3:0%}</> ATK as Physical damage twice to a ground enemy within the smoke and <$ba.stun>Stun</> them for <@ba.vup>{attack@stun}</>s (a single target can only be targeted once every <@ba.vup>{mark_duration}</>s)",
            "range": "x-1",
            "maxCharge": 0,
            "spCost": 0,
            "initSp": 0,
            "duration": 16.0,
            "blackboard": {
                "attack@s3_cd": 2.0,
                "attack@times": 2.0,
                "attack@hit_interval": 0.1,
                "attack@atk_scale_s3": 1.9,
                "attack@stun": 1.5,
                "mark_duration": 6.0
            }
        },
        {
            "description": "After deployment, Talent 1's range expands; Crownslayer disappears within the smoke, gaining <$ba.invisible>Invisibility</> and her Block becomes 0; every <@ba.vup>{attack@times}</>s, she will appear and deal <@ba.vup>{attack@atk_scale_s3:0%}</> ATK as Physical damage twice to a ground enemy within the smoke and <$ba.stun>Stun</> them for <@ba.vup>{attack@stun}</>s (a single target can only be targeted once every <@ba.vup>{mark_duration}</>s)",
            "range": "x-1",
            "maxCharge": 0,
            "spCost": 0,
            "initSp": 0,
            "duration": 16.0,
            "blackboard": {
                "attack@s3_cd": 2.0,
                "attack@times": 2.0,
                "attack@hit_interval": 0.1,
                "attack@atk_scale_s3": 2.1,
                "attack@stun": 2.0,
                "mark_duration": 6.0
            }
        },
        {
            "description": "After deployment, Talent 1's range expands; Crownslayer disappears within the smoke, gaining <$ba.invisible>Invisibility</> and her Block becomes 0; every <@ba.vup>{attack@times}</>s, she will appear and deal <@ba.vup>{attack@atk_scale_s3:0%}</> ATK as Physical damage twice to a ground enemy within the smoke and <$ba.stun>Stun</> them for <@ba.vup>{attack@stun}</>s (a single target can only be targeted once every <@ba.vup>{mark_duration}</>s)",
            "range": "x-1",
            "maxCharge": 0,
            "spCost": 0,
            "initSp": 0,
            "duration": 16.0,
            "blackboard": {
                "attack@s3_cd": 2.0,
                "attack@times": 2.0,
                "attack@hit_interval": 0.1,
                "attack@atk_scale_s3": 2.3,
                "attack@stun": 3.0,
                "mark_duration": 6.0
            }
        },
        {
            "description": "After deployment, Talent 1's range expands; Crownslayer disappears within the smoke, gaining <$ba.invisible>Invisibility</> and her Block becomes 0; every <@ba.vup>{attack@times}</>s, she will appear and deal <@ba.vup>{attack@atk_scale_s3:0%}</> ATK as Physical damage twice to a ground enemy within the smoke and <$ba.stun>Stun</> them for <@ba.vup>{attack@stun}</>s (a single target can only be targeted once every <@ba.vup>{mark_duration}</>s)",
            "range": "x-1",
            "maxCharge": 0,
            "spCost": 0,
            "initSp": 0,
            "duration": 16.0,
            "blackboard": {
                "attack@s3_cd": 2.0,
                "attack@times": 2.0,
                "attack@hit_interval": 0.1,
                "attack@atk_scale_s3": 2.5,
                "attack@stun": 4.0,
                "mark_duration": 6.0
            }
        }
    ]
}