{
    "id": "skchr_savage_1",
    "name": "Power Strike \u03b2",
    "skillType": "AUTO",
    "durationType": "NONE",
    "spType": "INCREASE_WHEN_ATTACK",
    "levels": [
        {
            "description": "Increases the ATK of next attack to <@ba.vup>{atk_scale:0%}</>",
            "maxCharge": 1,
            "spCost": 5,
            "initSp": 0,
            "duration": 0.0,
            "blackboard": {
                "atk_scale": 1.7
            }
        },
        {
            "description": "Increases the ATK of next attack to <@ba.vup>{atk_scale:0%}</>",
            "maxCharge": 1,
            "spCost": 5,
            "initSp": 0,
            "duration": 0.0,
            "blackboard": {
                "atk_scale": 1.75
            }
        },
        {
            "description": "Increases the ATK of next attack to <@ba.vup>{atk_scale:0%}</>",
            "maxCharge": 1,
            "spCost": 5,
            "initSp": 0,
            "duration": 0.0,
            "blackboard": {
                "atk_scale": 1.8
            }
        },
        {
            "description": "Increases the ATK of next attack to <@ba.vup>{atk_scale:0%}</>",
            "maxCharge": 1,
            "spCost": 4,
            "initSp": 0,
            "duration": 0.0,
            "blackboard": {
                "atk_scale": 1.85
            }
        },
        {
            "description": "Increases the ATK of next attack to <@ba.vup>{atk_scale:0%}</>",
            "maxCharge": 1,
            "spCost": 4,
            "initSp": 0,
            "duration": 0.0,
            "blackboard": {
                "atk_scale": 1.9
            }
        },
        {
            "description": "Increases the ATK of next attack to <@ba.vup>{atk_scale:0%}</>",
            "maxCharge": 1,
            "spCost": 4,
            "initSp": 0,
            "duration": 0.0,
            "blackboard": {
                "atk_scale": 1.95
            }
        },
        {
            "description": "Increases the ATK of next attack to <@ba.vup>{atk_scale:0%}</>",
            "maxCharge": 1,
            "spCost": 4,
            "initSp": 0,
            "duration": 0.0,
            "blackboard": {
                "atk_scale": 2.0
            }
        },
        {
            "description": "Increases the ATK of next attack to <@ba.vup>{atk_scale:0%}</>",
            "maxCharge": 1,
            "spCost": 4,
            "initSp": 0,
            "duration": 0.0,
            "blackboard": {
                "atk_scale": 2.1
            }
        },
        {
            "description": "Increases the ATK of next attack to <@ba.vup>{atk_scale:0%}</>",
            "maxCharge": 1,
            "spCost": 4,
            "initSp": 0,
            "duration": 0.0,
            "blackboard": {
                "atk_scale": 2.2
            }
        },
        {
            "description": "Increases the ATK of next attack to <@ba.vup>{atk_scale:0%}</>",
            "maxCharge": 1,
            "spCost": 3,
            "initSp": 0,
            "duration": 0.0,
            "blackboard": {
                "atk_scale": 2.3
            }
        }
    ]
}