{
    "id": "sktok_skztxy_1",
    "name": "Shock of Will",
    "skillType": "AUTO",
    "durationType": "NONE",
    "spType": "INCREASE_WITH_TIME",
    "levels": [
        {
            "description": "Strikes all allied units on the field once with Arts damage and summons several enemies; the damage dealt gradually increases every time Shock of Will is cast",
            "maxCharge": 1,
            "spCost": 100,
            "initSp": 0,
            "duration": -1.0,
            "blackboard": {
                "atk_scale_add": 0.2,
                "atk_scale_now": 0.5,
                "atk_scale_max": 5.0
            }
        }
    ]
}