{
    "id": "sktok_factory_1",
    "name": "Production Line",
    "skillType": "MANUAL",
    "durationType": "NONE",
    "spType": "INCREASE_WITH_TIME",
    "levels": [
        {
            "description": "Recover <@ba.vup>1</> SP every second for every neighboring allied unit; Neighboring allied units have <@ba.vup>50%</> reduced DEF and become more likely to be attacked by enemies; Consumes <@ba.vup>{cost}</> DP to deploy a Second-hand Drone at the corresponding location in the <@ba.vup>Lower Level Test Area</>",
            "range": "x-5",
            "maxCharge": 1,
            "spCost": 50,
            "initSp": 0,
            "duration": 0.0,
            "blackboard": {
                "cost": 10.0
            }
        }
    ]
}