{
    "id": "sktok_acarm023_1",
    "name": "Coin-Operated Machine",
    "skillType": "PASSIVE",
    "durationType": "NONE",
    "spType": 8,
    "levels": [
        {
            "description": "Stores <@ba.vup>1</> Funds every time you purchase an Operator with the same Class as the equipped Operator. You will receive the stored Funds when this equipment is replaced (max <@ba.vup>10</> Funds)",
            "maxCharge": 0,
            "spCost": 0,
            "initSp": 0,
            "duration": 0.0,
            "blackboard": {}
        }
    ]
}