{
    "id": "sktok_xbdrill",
    "name": "Gather",
    "skillType": "AUTO",
    "durationType": "NONE",
    "spType": "INCREASE_WITH_TIME",
    "levels": [
        {
            "description": "Produces <Master Gatherers> to gather from <Thickets>, <Monoliths>, <Strange Ore Veins>, and <Glowstone Ore Veins> with a bonus when gathering from <Glowstone Ore Veins>. Limit of 3.",
            "maxCharge": 1,
            "spCost": 10,
            "initSp": 5,
            "duration": -1.0,
            "blackboard": {
                "cost": 0.0,
                "enemy_key": 0.0,
                "max_cnt": 3.0,
                "extra_count": 0.0,
                "live_duration": 9999.0,
                "sandbox_res_collector.hp_ratio[wood]": 0.008,
                "sandbox_res_collector.hp_ratio[stone]": 0.006,
                "sandbox_res_collector.hp_ratio[iron]": 0.005
            }
        }
    ]
}